AUTHORS.rst
CHANGES.rst
renku/__init__.py
renku/command/__init__.py
renku/command/checks/__init__.py
renku/command/checks/activities.py
renku/command/checks/datasets.py
renku/command/checks/githooks.py
renku/command/checks/migration.py
renku/command/checks/project.py
renku/command/checks/storage.py
renku/command/checks/validate_shacl.py
renku/command/checks/workflow.py
renku/command/clone.py
renku/command/command_builder/__init__.py
renku/command/command_builder/command.py
renku/command/command_builder/communication.py
renku/command/command_builder/database.py
renku/command/command_builder/gitlab.py
renku/command/command_builder/lock.py
renku/command/command_builder/migration.py
renku/command/command_builder/repo.py
renku/command/command_builder/storage.py
renku/command/config.py
renku/command/dataset.py
renku/command/doctor.py
renku/command/format/__init__.py
renku/command/format/activity.py
renku/command/format/dataset_files.py
renku/command/format/dataset_tags.py
renku/command/format/datasets.py
renku/command/format/json.py
renku/command/format/session.py
renku/command/format/storage.py
renku/command/format/tabulate.py
renku/command/format/workflow.py
renku/command/gc.py
renku/command/githooks.py
renku/command/graph.py
renku/command/group.py
renku/command/init.py
renku/command/lfs.py
renku/command/log.py
renku/command/login.py
renku/command/mergetool.py
renku/command/migrate.py
renku/command/move.py
renku/command/options.py
renku/command/project.py
renku/command/remove.py
renku/command/rerun.py
renku/command/rollback.py
renku/command/run.py
renku/command/save.py
renku/command/schema/__init__.py
renku/command/schema/activity.py
renku/command/schema/agent.py
renku/command/schema/annotation.py
renku/command/schema/calamus.py
renku/command/schema/composite_plan.py
renku/command/schema/dataset.py
renku/command/schema/entity.py
renku/command/schema/image.py
renku/command/schema/parameter.py
renku/command/schema/plan.py
renku/command/schema/project.py
renku-2.9.4.dist-info/AUTHORS.rst
renku-2.9.4.dist-info/LICENSE
renku-2.9.4.dist-info/METADATA
renku-2.9.4.dist-info/WHEEL
renku-2.9.4.dist-info/entry_points.txt
renku-2.9.4.dist-info/RECORD
