Metadata-Version: 2.1
Name: renku
Version: 2.9.4
Summary: Python SDK and CLI for the Renku platform.
Home-page: https://github.com/swissdatasciencecenter/renku-python
License: Apache-2.0
Keywords: Renku,CLI
Author: Swiss Data Science Center
Author-email: contact@datascience.ch
Requires-Python: >=3.8.1,<3.12
Classifier: Development Status :: 4 - Beta
Classifier: Environment :: Web Environment
Classifier: Intended Audience :: Developers
Classifier: Intended Audience :: Science/Research
Classifier: License :: OSI Approved :: Apache Software License
Classifier: Operating System :: OS Independent
Classifier: Programming Language :: Python
Classifier: Programming Language :: Python :: 3
Classifier: Programming Language :: Python :: 3.9
Classifier: Programming Language :: Python :: 3.10
Classifier: Programming Language :: Python :: 3.11
Classifier: Programming Language :: Python :: 3.8
Classifier: Topic :: Internet :: WWW/HTTP :: Dynamic Content
Classifier: Topic :: Software Development :: Libraries :: Python Modules
Provides-Extra: service
Requires-Dist: apispec (>=6.3.0,<6.4.0) ; extra == "service"
Requires-Dist: apispec-oneofschema (>=3.0.0,<4.0.0) ; extra == "service"
Requires-Dist: apispec-webframeworks (>=0.5,<0.6) ; extra == "service"
Requires-Dist: attrs (>=23.1.0,<24.0.0)
Requires-Dist: bashlex (>=0.16,<0.17)
Requires-Dist: calamus (>=0.4,<0.5)
Requires-Dist: circus (>=0.18,<0.19) ; extra == "service"
Requires-Dist: click (>=8.1.7,<8.2.0)
Requires-Dist: click-option-group (>=0.5.2,<0.6.0)
Requires-Dist: click-plugins (>=1.1.1,<1.2.0)
Requires-Dist: coverage[toml] (>=6.0,<7.0)
Requires-Dist: cryptography (>=41.0.7,<42.0.0)
Requires-Dist: cwl-utils (>=0.27,<0.28)
Requires-Dist: cwltool (==3.1.20230601100705)
Requires-Dist: deal (>=4.24.3,<4.25.0)
Requires-Dist: deepdiff (>=6.7.1,<6.8.0)
Requires-Dist: deepmerge (>=1.1.0,<1.2.0)
Requires-Dist: docker (>=5.0.3,<6.0.0)
Requires-Dist: filetype (>=1.2.0,<2.0.0)
Requires-Dist: flask (>=2.3.3,<4.0.0) ; extra == "service"
Requires-Dist: gitpython (>=3.1.41,<3.2.0)
Requires-Dist: grandalf (>=0.8,<0.9)
Requires-Dist: gunicorn ; extra == "service"
Requires-Dist: humanize (>=4.9.0,<4.10.0)
Requires-Dist: importlib-resources (>=5.12,<6.2)
Requires-Dist: inject (>=4.3.1,<4.4.0)
Requires-Dist: jinja2 (>=3.1.2,<3.2.0)
Requires-Dist: marshmallow (>=3.19.0,<3.20.0) ; extra == "service"
Requires-Dist: marshmallow-oneofschema (>=3.0.1,<4.0.0) ; extra == "service"
Requires-Dist: networkx (>=3.1,<3.2)
Requires-Dist: orjson (>=3.9.10,<4.0.0)
Requires-Dist: packaging (>=23.2,<24.0)
Requires-Dist: pathspec (>=0.11,<0.12)
Requires-Dist: patool (>=1.12,<1.13)
Requires-Dist: pillow (>=10.1.0,<11.0.0) ; extra == "service"
Requires-Dist: pluggy (>=1.3.0,<1.4.0)
Requires-Dist: poetry-dynamic-versioning (>=1.2.0,<2.0.0)
Requires-Dist: portalocker (>=2.7.0,<2.8.0)
Requires-Dist: prometheus-flask-exporter (>=0.23,<0.24)
Requires-Dist: psutil (>=5.9.6,<5.10.0)
Requires-Dist: pydantic (>=2.5.2,<2.6.0)
Requires-Dist: pyjwt (>=2.4,<2.9)
Requires-Dist: pyld (>=2.0.3,<2.1.0)
Requires-Dist: pyshacl (>=0.25,<0.26)
Requires-Dist: python-dateutil (>=2.8.2,<2.9.0)
Requires-Dist: python-dotenv (>=0.20,<0.21) ; extra == "service"
Requires-Dist: python-gitlab (>=4.2.0,<4.3.0)
Requires-Dist: pyyaml (>=6.0.1,<6.1.0)
Requires-Dist: rdflib (>=6.3.2,<7.0.0)
Requires-Dist: redis (>=5.0.1,<5.1.0) ; extra == "service"
Requires-Dist: requests (>=2.31.0,<2.32.0)
Requires-Dist: rich (>=13.7.0,<14.0.0)
Requires-Dist: rq (>=1.15.1,<1.16.0) ; extra == "service"
Requires-Dist: sentry-sdk[flask] (>=1.39.0,<1.40.0) ; extra == "service"
Requires-Dist: shellingham (>=1.5.4,<1.6.0)
Requires-Dist: tabulate (>=0.9,<0.10)
Requires-Dist: toil (>=5.12.0,<5.13.0)
Requires-Dist: tqdm (>=4.66.1,<4.67.0)
Requires-Dist: walrus (>=0.9,<0.10) ; extra == "service"
Requires-Dist: werkzeug (>=3.0.1,<3.1.0)
Requires-Dist: yagup (>=0.1,<0.2)
Requires-Dist: yaspin (>=2.5.0,<2.6.0)
Requires-Dist: zc.relation (>=2.0,<2.1)
Requires-Dist: zodb (>=5.8.1,<5.9.0)
Requires-Dist: zstandard (>=0.22,<0.23)
Project-URL: Changelog, https://github.com/swissdatasciencecenter/renku-python/blob/master/CHANGES.rst
Project-URL: Documentation, https://renku-python.rtfd.io/
